mathprimes.py
mathprimes-1.0.2.dist-info/WHEEL
mathprimes-1.0.2.dist-info/METADATA
mathprimes-1.0.2.dist-info/RECORD
