Metadata-Version: 2.1
Name: mathprimes
Version: 1.0.2
Summary: Well documented, super fast, prime number methods using mathematical algorithms.
Home-page: https://github.com/GrandMoff100/MathPrimes
License: MIT
Author: GrandMoff100
Author-email: nlarsen23.student@gmail.com
Requires-Python: >=3.8,<4.0
Classifier: License :: OSI Approved :: MIT License
Classifier: Programming Language :: Python :: 3
Classifier: Programming Language :: Python :: 3.8
Classifier: Programming Language :: Python :: 3.9
Project-URL: Repository, https://github.com/GrandMoff100/MathPrimes
